<?xml version='1.0' encoding='utf-8'?>
<i><chatserver>chat.bilibili.com</chatserver><chatid>0</chatid><mission>0</mission><maxlimit>3000</maxlimit><state>0</state><real_name>0</real_name><source>e-r</source><d p="83.97200,1,25,16777215,1727539429,0,e3c6743a,1681481624572721664,10">香港小孩姐立正了</d><d p="137.20600,1,25,16777215,1727539509,0,e3c6743a,1681482292431954688,11">这段蚌埠住了</d><d p="98.50100,1,25,16777215,1727539589,0,62840acd,1681482963277627904,9">出音味来</d><d p="115.97900,5,25,16777215,1727539975,0,4e9f3961,1681486200684733440,10">钓蟹钓蟹，我中意钓蟹，钓蟹真快乐</d><d p="102.89300,1,25,16777215,1727540155,0,942b7cc4,1681487708025702912,9">做了一晚泥工~~</d><d p="0.00000,1,25,16777215,1727540928,0,68bbfd64,1681494198492258560,9">艹，开幕雷击</d><d p="79.22600,1,25,16777215,1727540980,0,86dbbf15,1681494636033753088,11">神经，害我笑了一下</d><d p="43.74100,1,25,16777215,1727541040,0,68bbfd64,1681495136187677440,9">广东人是真的喜欢beyond</d><d p="109.61600,1,25,16777215,1727541061,0,b6e504ca,1681495313381002496,11">钓蟹～钓蟹～，我中意钓蟹～，钓蟹真快乐～</d><d p="62.01400,1,25,16777215,1727541118,0,68bbfd64,1681495789526092544,9">九龙（东京）</d><d p="193.19700,1,25,16777215,1727541162,0,b6e504ca,1681496157694380800,9">神人笑声绷不住了</d><d p="98.84000,1,25,16777215,1727541211,0,68bbfd64,1681496567074459136,9">我去，两广共同省歌</d><d p="117.76400,1,25,16777215,1727541255,0,68bbfd64,1681496936382880256,11">大力X去~</d><d p="123.74100,1,25,16777215,1727541271,0,68bbfd64,1681497070801899008,9">有没有可能他在假唱？</d><d p="156.72500,1,25,16777215,1727541317,0,68bbfd64,1681497457240091648,10">这也能cue到小祥</d><d p="161.25000,1,25,16777215,1727541329,0,68bbfd64,1681497559580902400,11">成语是不是用错了？</d><d p="182.32400,1,25,16777215,1727541434,0,68bbfd64,1681498443471963392,11">鳗！</d><d p="216.73900,5,25,16646914,1727541516,0,68bbfd64,1681499127764274176,11">注：粤语里面“花桥”和英文的FA Q同音</d><d p="237.57500,1,25,16777215,1727541573,0,68bbfd64,1681499610729963776,10">谷恒条野~~</d><d p="261.86700,1,25,16777215,1727541637,0,68bbfd64,1681500139774218240,11">格局大了</d><d p="285.26500,1,25,16777215,1727541676,0,68bbfd64,1681500473733109760,9">哈哈哈哈哈哈哈哈哈哈</d><d p="309.87600,1,25,16777215,1727541729,0,68bbfd64,1681500911869897728,11">冷知识，呼噜大小和体型无关</d><d p="341.18600,1,25,16777215,1727541779,0,68bbfd64,1681501330654432512,11">要进主线了嘛</d><d p="346.83800,1,25,16777215,1727541793,0,68bbfd64,1681501456307552768,11">黄家驹</d><d p="355.44200,1,25,16777215,1727542210,0,68bbfd64,1681504953677656832,11">欸。。我是广东人，也很少听粤语歌了，要听也只是听老歌</d><d p="142.66600,1,25,16777215,1727542364,0,68bbfd64,1681506243493268480,11">耳背mmk</d><d p="15.96200,5,25,16777215,1727543558,0,d0911519,1681516259197383424,11">卖鱼强</d><d p="116.53200,1,25,16777215,1727544693,0,cc130a59,1681525783153376768,11">广东儿歌</d><d p="92.07200,1,25,16777215,1727544801,0,8051a4ee,1681526681271346432,11">小孩姐战士</d><d p="312.73400,1,25,15138834,1727545053,0,dde2b7e9,1681528800174816000,9">梦回东方有声漫19</d><d p="323.55200,1,25,16777215,1727545252,0,8051a4ee,1681530468107055616,11">哈基米</d><d p="77.85900,1,25,16777215,1727545837,0,5abefae1,1681535373722922752,10">草草草</d><d p="9.90400,5,25,15772458,1727548241,0,267a0e4e,1681555540473565952,11">港铁动感号动车（确信）</d><d p="101.48100,1,25,16777215,1727548348,0,a57f30ed,1681556438457533696,9">哇，做一晚泥工</d><d p="265.74900,1,25,16777215,1727548909,0,48dfd0c2,1681561142478584832,11">最为最早的二次元扩散区域，格局大是常规操作吗哈哈哈ww</d><d p="229.17100,1,25,16777215,1727553766,0,d811281e,1681601885762772992,11">笑不活了</d><d p="4.97500,5,25,16707842,1727556888,0,e5c1d1b,1681628078361439488,10">香港西九龙</d><d p="42.08000,1,25,16777215,1727567388,0,7c84c9db,1681716161873654784,10">上一次听到有人要做第二个beyond，还是在古惑仔里</d><d p="122.98500,5,25,16777215,1727568458,0,db824e08,1681725132835614208,10">狠狠拷打原作第一集最后明明只有吉他鼓手和主唱 但是最后的空之箱却啥都有的偷懒行为</d><d p="129.75800,5,25,16777215,1727568479,0,db824e08,1681725309289942528,11">《soulmate》</d><d p="87.59200,5,25,16707842,1727569886,0,5d28bb43,1681737109679438592,10">海 港 城</d><d p="191.26200,1,25,16777215,1727571669,0,e11c8218,1681752066978096128,11">拟人笑声</d><d p="12.51400,5,25,16707842,1727574163,0,723183e5,1681772993358989824,10">西 九 龙 站</d><d p="128.19000,1,25,16777215,1727574461,0,9433d196,1681775491838776064,8">史忽与蟹都有洞~</d><d p="165.56500,5,25,16707842,1727577345,0,3180b6ae,1681799683712228352,11">低 音 吉 他</d><d p="234.74000,1,25,16777215,1727579255,0,c19760a3,1681815703571606784,11">上一次见到这种名字，还是喜多郁代</d><d p="236.21600,1,25,16777215,1727579315,0,765e6535,1681816206946757120,9">不是大快活？</d><d p="53.83800,5,25,15138834,1727579898,0,b78dd1f3,1681821103460457984,10">香港下雪那真的是……</d><d p="117.42000,1,25,16777215,1727579935,0,98cea329,1681821413478884352,9">mmk的声线真俊呀</d><d p="30.34000,1,25,16777215,1727580153,0,b7098821,1681823235601368832,11">还真是西九龙(</d><d p="296.65700,5,25,16777215,1727580254,0,73fc4730,1681824090467544064,10">九龙城寨</d><d p="153.07300,1,25,16777215,1727580506,0,9dcfabc6,1681826199212473856,9">上个第一次见面就要组band的人还是祥子</d><d p="272.48200,1,25,16777215,1727581100,0,11295a34,1681831182960103168,9">香港邊有吉野家開廿四</d><d p="54.31500,5,25,16777215,1727582752,0,3a6365d4,1681845039959456000,11">唔↓嗷↑</d><d p="66.08900,1,25,16777215,1727583513,0,7c2a1d1b,1681851425510135040,9">重  庆  大  厦</d><d p="51.17200,1,25,16777215,1727583620,0,f023b1ed,1681852324315806208,11">但是气候可能要问特异人士</d><d p="128.99300,1,25,16777215,1727583887,0,5ab7eba3,1681854565332824064,10">台长，何时来的？</d><d p="63.14300,5,25,41194,1727584858,0,5a53cacb,1681862709722904320,10">敏華冰廳</d><d p="168.95200,1,25,16777215,1727586123,0,31b36d96,1681873317143728128,9">罗湖草</d><d p="42.34200,1,25,16777215,1727586342,0,24820a99,1681875154768207360,11">不是红堪？</d><d p="298.15700,5,25,15138834,1727588012,0,96d05ade,1681889168013202944,11">太平山小别墅</d><d p="29.39700,1,25,16777215,1727589441,0,3d2d0a16,1681901150275675904,9">从西九龙坐过来的是吧</d><d p="240.02500,1,25,16777215,1727589773,0,3d2d0a16,1681903941190725888,8">天才啊</d><d p="172.96500,1,25,16777215,1727590170,0,5a156c28,1681907266057474560,9">打进尖沙咀啦</d><d p="5.81300,1,25,16777215,1727590583,0,360bb8d1,1681910729932747264,11">开幕雷击</d><d p="90.13500,1,25,16777215,1727590676,0,f77e59dc,1681911515457854976,9">铜锣湾时代广场（确信）</d><d p="242.92700,1,25,16777215,1727591394,0,f77e59dc,1681917537681647872,10">这下真是牛牛了</d><d p="272.46600,1,25,16777215,1727591445,0,f77e59dc,1681917959402025984,11">hk的蛮大有多大（思考）</d><d p="153.91700,1,25,16777215,1727591678,0,2afc47f5,1681919917714607104,10">。。。。羽毛球绷不住了</d><d p="350.98600,1,25,16777215,1727592236,0,e2f6d598,1681924594631726080,9">正确的</d><d p="50.71100,5,25,16777215,1727592719,0,c12789fd,1681928648553082368,11">霸王级寒潮</d><d p="43.38100,1,25,16777215,1727592732,0,e5452db2,1681928759735700992,9">做BYD就有</d><d p="64.18500,1,25,16777215,1727594016,0,c69d2d88,1681939528383819008,11">红 茶 冰 室 </d><d p="46.96500,1,25,16777215,1727594196,0,5d4e549e,1681941042351664384,9">做byd的笑死我了哈哈哈哈</d><d p="191.61600,1,25,16777215,1727595284,0,b9450da0,1681950171137055744,9">古天乐草</d><d p="186.37000,1,25,16777215,1727595305,0,50b5892b,1681950342843846656,9">永远怀念</d><d p="98.77000,1,25,16777215,1727596218,0,684fa70a,1681958000216223744,9">这下对味儿了</d><d p="243.08800,1,25,16777215,1727597281,0,6637c6d0,1681966916912976896,11">唔系大家乐？</d><d p="30.32700,5,25,16777215,1727597747,0,984fa718,1681970829325337088,10">东涌线</d><d p="351.33100,1,25,16777215,1727597826,0,79c70fa1,1681971488050034688,11">还真是</d><d p="88.10500,5,25,15138834,1727597829,0,984fa718,1681971520085432832,10">圍方</d><d p="211.55600,5,25,15138834,1727597972,0,984fa718,1681972717425007104,10">堅拿道</d><d p="32.73800,1,25,16777215,1727599056,0,8068349f,1681981808923532544,9">九龙上的车（）</d><d p="23.57700,1,25,16777215,1727599113,0,1bf78f25,1681982287895560704,9">还是老哥你的配音听着舒服</d><d p="255.44700,5,25,14811775,1727600902,0,e5f9348c,1681997291927683584,10">笑死我了这里</d><d p="83.32600,1,25,16777215,1727601317,0,2bd04120,1682000772495190528,9">细节繁体字（</d><d p="152.71000,1,25,16777215,1727601457,0,2bd04120,1682001950045936384,11">最主动的一集</d><d p="145.80000,1,25,16777215,1727601764,0,eef3e56f,1682004529408790016,10">好撚好听啊，简直你老味天籁啊！</d><d p="272.64100,1,25,16777215,1727602274,0,2d0ff5fa,1682008801366289408,8">很大意思是只有四十平米</d><d p="234.49800,1,25,16777215,1727602313,0,8fc447b7,1682009127808928256,9">大家乐</d><d p="217.40500,5,25,16777215,1727603142,0,191a322c,1682016080967054848,10">沪11＆苏11：得亏咱们的羁绊之处不在粤语区吼（指花桥站）</d><d p="320.86800,1,25,16777215,1727604194,0,6b60e84,1682024908097427712,11">合着是伏笔是吧</d><d p="109.47200,1,25,16777215,1727605048,0,6691a33c,1682032070434402560,9">做一晚泥工(  )</d><d p="156.28200,1,25,41194,1727605470,0,16f5cfcd,1682035617489888000,11">大祥老师：干什么了？</d><d p="200.17800,1,25,16777215,1727605622,0,fa7e3c6e,1682036884706087680,11">特醇米酒</d><d p="168.22600,1,25,16777215,1727606473,0,126a45a3,1682044029904297984,8">当主唱还是太难了，干脆做贝斯手</d><d p="227.65700,1,25,16777215,1727606485,0,4094862d,1682044125752675328,9">bo野家</d><d p="45.00800,5,25,14811775,1727607900,0,f820b576,1682055998594418688,10">目标！红磡！</d><d p="333.34200,5,25,14811775,1727608272,0,f820b576,1682059122613023488,11">最合理的理由</d><d p="112.05700,1,25,16777215,1727608363,0,62e9be56,1682059884852299008,9">这下听不懂了</d><d p="357.65700,1,25,16777215,1727608781,0,f9ee36e5,1682063387825952000,8">草，伤心了</d><d p="42.39200,1,25,16777215,1727608991,0,77a7f424,1682065149374217728,9">粤语区对beyond的执念</d><d p="41.23500,1,25,16777215,1727609098,0,77a7f424,1682066047349552896,10">我哋首选红馆啦</d><d p="142.79200,1,25,16777215,1727609304,0,77a7f424,1682067779118819584,8">靓女！</d><d p="256.49800,1,25,16777215,1727609547,0,77a7f424,1682069814094391040,11">Cantonese only！</d><d p="349.99500,1,25,16777215,1727609670,0,77a7f424,1682070841950511872,9">唯一实话</d><d p="308.73900,1,25,16777215,1727610580,0,1cba0212,1682078481246606848,10">离岛村屋</d><d p="317.75500,5,25,15138834,1727611088,0,c21d9f45,1682082742692739584,10">VTEC KICK IN YO</d><d p="91.72800,5,25,16777215,1727611466,0,feec3514,1682085909157202432,10">K11（</d><d p="76.42100,1,25,16777215,1727611932,0,3ac50028,1682089822862222848,9">逆天</d><d p="53.80200,1,25,16777215,1727612515,0,90490ea4,1682094712212963328,9">特异人士哦</d><d p="84.95600,5,25,14811775,1727613648,0,afb0053,1682104219248732160,11">币！(隔壁广州粤语版)</d><d p="116.27400,5,25,15138834,1727613729,0,afb0053,1682104893206279680,10">甚至跟画面对上了 (这一幕的画面确实像有一阵风)</d><d p="241.53100,1,25,16777215,1727614213,0,f2b854b4,1682108958736959744,9">不是大家乐？</d><d p="55.40800,5,25,16777215,1727614364,0,6ecbf28e,1682110219427579392,10">換季要靠特異人士</d><d p="170.70000,5,25,16777215,1727614494,0,6ecbf28e,1682111310920025088,10">不是宝安？</d><d p="314.69600,1,25,16777215,1727614497,0,3e54ad99,1682111340967319040,9">長州村屋</d><d p="38.23900,5,25,16707842,1727614628,0,ddd271a2,1682112435152145920,10">这下看懂了</d><d p="2.68500,1,25,16777215,1727614789,0,31bd09d9,1682113790289903360,9">开幕雷击</d><d p="137.53400,1,25,16777215,1727614798,0,4383b8c3,1682113860946967808,9">神经啊~~~笑死了~~~</d><d p="103.92600,1,25,16777215,1727615083,0,15850573,1682116249327196160,9">哇，仲有咸湿歌仔听</d><d p="153.64000,1,25,16777215,1727615773,0,e7690793,1682122044646708224,9">应该是爱音吧</d><d p="135.98400,1,25,16777215,1727615780,0,c897377,1682122098896434176,10">哈哈这里好有老港片的感觉哈哈</d><d p="99.67500,5,25,16707842,1727616291,0,d5494f96,1682126386011965952,10">风中风中！</d><d p="136.23200,1,25,16777215,1727617392,0,8756cb94,1682135624032950016,9">世界上有三种人……</d><d p="171.44100,1,25,16777215,1727617507,0,acb7fa56,1682136589116975616,9">姜涛</d><d p="206.67500,1,25,16777215,1727618648,0,bcd2b057,1682146159017657600,9">剧情咋变了？</d><d p="170.72200,1,25,16777215,1727619555,0,2aa1ea40,1682153764338865920,9">火到罗湖哈哈哈哈哈哈哈哈哈</d><d p="172.42400,5,25,16777215,1727619567,0,2aa1ea40,1682153865715384832,11">不是龙岗？不是龙岗？</d><d p="225.37300,1,25,16777215,1727620102,0,500956c0,1682158357689427456,10">嘎文名哈哈哈</d><d p="313.00500,1,25,16777215,1727620309,0,500956c0,1682160094567952896,11">笑点解析：英语比原版准多了</d><d p="237.89300,5,25,15138834,1727621014,0,87375f36,1682166006858084096,11">冚家乐</d><d p="102.12700,1,25,16777215,1727621258,0,88e34e31,1682168051623351296,11">省歌233</d><d p="136.74400,1,25,16777215,1727621495,0,760fc3f,1682170041325487872,10">有星爷电影无厘头的感觉了</d><d p="201.84900,1,25,16777215,1727622658,0,8a8dff6c,1682179797033430272,9">珍惜这句话吧</d><d p="7.94900,5,25,16777215,1727623011,0,f8cd6510,1682182760955783424,10">香 港 西 九 龙</d><d p="201.52200,5,25,15138834,1727623573,0,41bb95b9,1682187476141189120,10">深水埗</d><d p="232.11000,1,25,16777215,1727624602,0,b5fe35d1,1682196107423681024,9">人才</d><d p="254.96400,1,25,16777215,1727624674,0,b88fe0a,1682196709037514496,10">香港也有音读训读之争是吧</d><d p="2.88800,5,25,16777215,1727624761,0,e8cbf1ac,1682197440399093760,10">香港西九龙站</d><d p="73.86700,1,25,16777215,1727625234,0,5b3113e1,1682201407354213120,9">群租房来的喔，还便宜啊</d><d p="188.14800,1,25,16777215,1727626742,0,1ac281db,1682214056058125824,11">你币有了</d><d p="131.33900,5,25,15138834,1727626746,0,4b080243,1682214089981728256,10">台长?是你吗？</d><d p="171.65900,5,25,16777215,1727626796,0,4b080243,1682214505175644160,10">红磡见！</d><d p="251.63900,5,25,15138834,1727626885,0,4b080243,1682215258581896960,10">还以为是叉烧饭呢</d><d p="250.64900,1,25,16777215,1727627850,0,4708630f,1682223346550900480,10">不是牛don嗎</d><d p="163.25800,1,25,16707842,1727628076,0,5005aa43,1682225247794940672,10">都玩梗了不要在意成语对不对了。。。。。</d><d p="166.62400,1,25,16777215,1727628916,0,df9fa627,1682232296206108672,9">低音吉他</d><d p="63.48000,1,25,16777215,1727629106,0,b6a6d04d,1682233889344540928,10">九龙咖啡店</d><d p="62.13900,5,25,16777215,1727630981,0,9b05f287,1682249612339932160,10">《九龙尖沙咀》</d><d p="109.03900,5,25,16777215,1727631076,0,9b05f287,1682250415616218368,10">雕㩏雕㩏 我中意雕㩏</d><d p="116.79800,5,25,16777215,1727631122,0,9b05f287,1682250794294370560,10">大立插曲 对准个㩏龙</d><d p="122.69800,5,25,16777215,1727631156,0,9b05f287,1682251081722018048,11">look去悠悠弓</d><d p="124.73800,5,25,16777215,1727631186,0,9b05f287,1682251335267659776,10">炸波炸波 関西炸波</d><d p="128.23800,5,25,16777215,1727631215,0,9b05f287,1682251580030491904,10">亖呼与㩏都有姛</d><d p="74.16900,1,25,16777215,1727633977,0,337b19e4,1682274749600258048,10">逆天即兴表演</d><d p="320.94200,1,25,16777215,1727640621,0,a7714b50,1682330480064509184,9">梦回莲子</d><d p="97.70000,1,25,16777215,1727656207,0,f457a007,1682461227281870080,11">四驱小孩</d><d p="203.64000,1,25,16777215,1727657510,0,2aa0d18f,1682472159182526976,10">前往街头调查不当收入艺人的ICAC李香芹</d><d p="183.59900,1,25,16777215,1727658341,0,e7679d0f,1682479129520165632,9">斯人已逝</d><d p="210.66500,1,25,16777215,1727659218,0,8a3ed237,1682486487813437184,11">剧情改的好啊</d><d p="63.63600,5,25,16777215,1727659347,0,97715d93,1682487564080335872,10">九龍咖啡店</d><d p="288.31200,5,25,16777215,1727659613,0,a0625168,1682489800844603136,10">南亚人Rupa</d><d p="187.73900,1,25,16777215,1727661072,0,533f6cad,1682502036593340672,10">古天乐广告没绷住</d><d p="258.86100,5,25,15138834,1727667886,0,d348349,1682559193834259456,10">坎通（</d><d p="358.86100,5,25,15138834,1727668017,0,d348349,1682560295006838528,10">也不是不听，漫步人生路我都听啊，很少发现有而已</d><d p="184.35600,1,25,16777215,1727669470,0,7ddc8ba,1682572480776912896,9">还是要学习一个</d><d p="197.84200,1,25,16777215,1727671500,0,d1731ead,1682589513728095744,8">那我缺的，卖黄碟这一块谁给我补上啊</d><d p="275.44300,1,25,16777215,1727675330,0,c00b8726,1682621644755890688,9">足足有500呎</d><d p="70.14600,1,25,16777215,1727675389,0,e5452db2,1682622136261199616,11">200蚊你执嗨到啦</d><d p="218.81700,1,25,16777215,1727675731,0,275e7a60,1682625009090268928,9">花桥辣椒酱啊</d><d p="236.11000,1,25,16777215,1727676470,0,4b9088ba,1682631203985694464,10">痴线啊哈哈哈哈哈</d><d p="99.10900,1,25,16777215,1727676757,0,5b0feb9b,1682633615819629312,9">做一晚泥工草</d><d p="97.18700,1,25,16777215,1727677082,0,ec924b0f,1682636338174574336,9">一股强劲的音乐....</d><d p="18.65700,5,25,15138834,1727677853,0,2dd1ca61,1682642809733046784,10">老板 我要一碗鱼丸粗面</d><d p="273.51000,5,25,16777215,1727682791,0,330394e3,1682684228904478976,10">屋企</d><d p="88.65400,1,25,16777215,1727688090,0,1b017b0e,1682728682378238720,10">中环交易广场</d><d p="92.42700,1,25,16777215,1727688280,0,4f0ed619,1682730270896018944,9">维港（确信）</d><d p="181.61100,1,25,16777215,1727691011,0,fd5fa478,1682753185167326208,9">你见过凌晨四点的西九龙吗</d><d p="178.45900,1,25,16777215,1727691086,0,5fec3b72,1682753815117569536,10">还真是</d><d p="219.00800,1,25,16777215,1727691171,0,5fec3b72,1682754526270249984,9">解释得太对了，路上的车都倒过来听</d><d p="136.05900,1,25,16777215,1727692487,0,b045c102,1682765568513968384,9">神经啊哈哈哈哈哈哈哈</d><d p="129.52400,1,25,16777215,1727693197,0,9ac02259,1682771520071740672,9">man~</d><d p="231.75200,1,25,16777215,1727693718,0,52663400,1682775891694387200,9">笑死了</d><d p="44.55400,1,25,16777215,1727695035,0,20bc5882,1682786940690161152,9">目标是红磡</d><d p="100.46800,1,25,16777215,1727697693,0,64d9359f,1682809232845561344,9">强劲の小曲</d><d p="217.93800,1,25,16777215,1727697866,0,64d9359f,1682810690609638400,9">埋下伏笔</d><d p="69.71300,1,25,16777215,1727700774,0,4e4615e4,1682835080999406080,9">《重庆大厦》</d><d p="274.05800,1,25,16777215,1727701222,0,4d3f6b7e,1682838842837514496,9">很大（指鸟笼）</d><d p="138.74900,1,25,16777215,1727702861,0,60cf3fe0,1682852591547941888,9">欸！为什么！为什么在最喜欢的部分停下！</d><d p="102.11400,5,25,16707842,1727703000,0,bf07b8c2,1682853753629352960,10">返工返工，我中意返工</d><d p="0.55900,5,25,16707842,1727706123,0,c239c72a,1682879955489164288,10">九  广  铁  路</d><d p="56.46200,5,25,16707842,1727706195,0,c239c72a,1682880557983782912,10">要开始了哟</d><d p="270.07600,1,25,16777215,1727706436,0,551a1bd2,1682882576031623168,9">gbcの小曲</d><d p="61.71100,1,25,16777215,1727706486,0,3cec01b3,1682882998095591680,9">卑面派对</d><d p="190.51000,1,25,16777215,1727706948,0,70491a96,1682886868791904256,9">谁家鸭子</d><d p="5.15900,5,25,16777215,1727706998,0,c8788c6b,1682887292458969600,10">b e y o n d</d><d p="102.76700,1,25,16777215,1727707302,0,bfefb1e,1682889839735630592,9">广东人特有倒吸气</d><d p="82.89900,1,25,16777215,1727707418,0,9209f302,1682890819129915648,11">哈哈</d><d p="142.91700,1,25,16777215,1727707572,0,ff1579a4,1682892103887168000,10">酷狗</d><d p="190.70100,5,25,8700107,1727709531,0,98b91ea8,1682908540962009344,9">大晚上的是想笑死我吗哈哈哈哈哈</d><d p="185.65700,5,25,16707842,1727712333,0,a3d2a3a5,1682932045230027008,10">缅怀</d><d p="76.34400,1,25,16777215,1727713779,0,8e1a0529,1682944177756788224,9">茄汁先啱</d><d p="160.08900,1,25,16777215,1727713877,0,18638b86,1682944994891219200,9">还能串到GO啊？</d><d p="17.90600,1,25,16777215,1727727527,0,580dc9a1,1683059503903881984,9">不是香港口音啊</d><d p="69.91000,1,25,16777215,1727727580,0,580dc9a1,1683059945170157568,10">顺德口音</d><d p="315.56000,1,25,16777215,1727733127,0,e24c16e8,1683106480368702976,11">最先睡着的人才有资格睡觉</d><d p="40.81100,1,25,16777215,1727742550,0,91340e47,1683185521541453056,11">三语广播对味了</d><d p="351.44400,1,25,16777215,1727742753,0,6d8c79e,1683187223681464064,9">这里绝了</d><d p="214.97800,1,25,16777215,1727743534,0,1b017b0e,1683193774546782976,10">中环至半山自动扶梯</d><d p="74.97900,1,25,16777215,1727745161,0,d9ec16ad,1683207429238097664,9">神金哈哈哈哈</d><d p="137.44400,5,25,16776960,1727746389,0,a616f212,1683217726849515264,10">叶世荣初遇黄家驹belike：</d><d p="103.15500,5,25,16777215,1727751038,0,4868016e,1683256728440892672,10">钓蟹钓蟹我中意钓蟹</d><d p="295.21000,5,25,16777215,1727751159,0,4868016e,1683257739595256576,10">回元朗了</d><d p="345.78500,1,25,16777215,1727751345,0,a210d120,1683259304960766976,9">冲这一句话，你币有了</d><d p="347.18400,5,25,16776960,1727753511,0,a616f212,1683277472570981632,10">呜呜呜呜黄家驹</d><d p="292.83300,5,25,16777215,1727753529,0,e6b3a34b,1683277623977724672,11">新 界 村 屋</d><d p="29.51200,1,25,16777215,1727753895,0,6b6c9e52,1683280694703214848,9">卧槽这一声给我干醒了</d><d p="94.69900,1,25,16777215,1727757525,0,af83eadd,1683311139796632576,11">四驱乐队</d><d p="125.14200,1,25,16777215,1727757721,0,686c879e,1683312783813208064,9">神吐槽</d><d p="238.32000,1,25,16777215,1727775229,0,bc6c8a8e,1683459656871356416,9">梗太密了草</d><d p="71.17900,1,25,16777215,1727777851,0,cb876e66,1683481650358962432,9">200港纸？？哪儿的酒店啊我去包年</d><d p="58.86200,1,25,16777215,1727779741,0,f3229a9c,1683497500591266304,11">香港下雪要追溯到1893年了</d><d p="20.91400,1,25,16777215,1727780316,0,79868c3,1683502328840164096,9">三蚊一颗，十蚊三颗？？？</d><d p="45.01900,5,25,16777215,1727781915,0,10a4358e,1683515743876199168,10">可以成为BYD</d><d p="189.13200,1,25,16777215,1727787938,0,8aab70b3,1683566269461041408,9">too森破！</d><d p="116.33900,1,25,16777215,1727789380,0,aac24ed2,1683578358895793408,10">笑不活了</d><d p="271.11700,5,25,16777215,1727792323,0,c6058a74,1683603046611696640,10">在  杰  难  逃</d><d p="28.79100,5,25,15138834,1727792776,0,80ca98fb,1683606853889656064,10">可换乘三号线</d><d p="98.55100,5,25,15138834,1727792857,0,80ca98fb,1683607533870470400,10">做一晚泥工</d><d p="229.11000,5,25,15138834,1727793015,0,80ca98fb,1683608854908368896,10">寿星公吊颈</d><d p="356.83600,1,25,3381759,1727794268,0,91309e61,1683619363292200448,9">最泪目的一集</d><d p="68.59300,1,25,16777215,1727794274,0,52e2d5c5,1683619419311360512,9">200不够，最少400</d><d p="283.50900,1,25,16777215,1727794571,0,52e2d5c5,1683621911072128512,10">香港的大，足足有500尺（50平方）！！</d><d p="2.05900,1,25,16777215,1727795127,0,ef30feb,1683626575087713536,9">看gbc学方言</d><d p="58.56000,1,25,16777215,1727797556,0,7a2656ca,1683646949926180864,9">大冰期到了</d><d p="247.73900,5,25,15138834,1727806657,0,55feab50,1683723292475565568,10">去吃牛展啦</d><d p="286.36300,5,25,15138834,1727809473,0,2aaa4c53,1683746917714539264,11">菲佣↓</d><d p="22.31400,1,25,16777215,1727838679,0,e7827180,1683991912346701312,11">说到鱼蛋就想起了乌蝇哥</d><d p="172.13900,5,25,14811775,1727838926,0,1d514448,1683993984483857920,10">nbuna是吧</d><d p="52.66100,1,25,16777215,1727841581,0,4393ed6c,1684016259483585536,9">细节海阔天空歌词</d><d p="35.51500,1,25,16777215,1727845645,0,f1855190,1684050349772004608,9">唔黑哈呀站tin后？</d><d p="98.04000,1,25,16777215,1727846406,0,bdc3f8e1,1684056731187858176,9">一阵强劲的音乐响起</d><d p="8.25900,1,25,16777215,1727846706,0,c374eca5,1684059247299871488,9">香港西九龙站</d><d p="21.64900,1,25,16777215,1727848902,0,45c97529,1684077666980750080,10">什么周星驰电影</d><d p="74.09500,1,25,16777215,1727858818,0,cd8f4334,1684160851597034752,9">哈哈，都知道200不可能</d><d p="357.05200,1,25,16777215,1727859118,0,cd8f4334,1684163369496030208,10">你话啊？</d><d p="242.17900,1,25,16777215,1727864493,0,5ef7e148,1684208454052509952,11">为什么不是大快活或大家乐hhh</d><d p="285.25500,1,25,16777215,1727864560,0,5ef7e148,1684209013983704576,9">花桥花桥花~</d><d p="125.56800,1,25,16777215,1727866570,0,3953b776,1684225883273922304,10">预置器也干了</d><d p="48.96100,5,25,16776960,1727876880,0,48660d25,1684312366953469952,10">哇！！香港落雪啦！！拍张照先（</d><d p="127.85600,1,25,16777215,1727877313,0,c4b339dd,1684315999396508160,11">抓波抓波</d><d p="150.24000,5,25,16777215,1727877692,0,a2dd0659,1684319177488059392,10">要组一辈子乐队吗？（有端联想）</d><d p="164.55500,1,25,16777215,1727878991,0,e903e512,1684330071135424768,9">曲词编监请揾林家谦</d><d p="350.87900,1,25,16777215,1727879239,0,e903e512,1684332155109270016,10">你不关注不代表没有哦 广东歌一直都在</d><d p="107.41900,1,25,16777215,1727880200,0,2bd7594d,1684340214799609344,9">钓蟹钓蟹</d><d p="149.34100,1,25,16777215,1727883158,0,1529c5fb,1684365032940917248,11">帮紧你，帮紧你</d><d p="272.97500,1,25,16777215,1727885523,0,f26e4435,1684384868215159296,10">牛肉饭の小曲</d><d p="54.17900,1,25,16777215,1727886225,0,2fb9ee8f,1684390756742002944,9">呀哈哈哈哈</d><d p="57.50600,5,25,16777215,1727886422,0,901db9cf,1684392406982075136,10">點解呀！（十分确信）</d><d p="194.54500,1,25,16777215,1727886717,0,dff1131,1684394887786759168,10">我真的要笑死了</d><d p="22.99900,1,25,16777215,1727894538,0,bdeb0c62,1684460490333428224,9">物价正确</d><d p="112.27000,1,25,16777215,1727900839,0,3715b8f4,1684513350534418176,9">最听不懂的一集</d><d p="282.94300,1,25,16777215,1727921413,0,f9904027,1684685939659743744,8">香港转台湾</d><d p="182.42200,1,25,16777215,1727933937,0,6e9a99aa,1684790992647563264,9">按5可奉告</d><d p="260.30400,1,25,16777215,1727934222,0,5076b4d,1684793385749140480,9">护国军！出动！</d><d p="201.93400,5,25,15138834,1727934251,0,53caeea8,1684793632500145408,10">？这都能接，多么丰矿</d><d p="116.37400,1,25,16777215,1727940945,0,2390801c,1684849777990711808,9">两广省歌</d><d p="107.61200,1,25,16777215,1727941579,0,39871e00,1684855102441316352,9">潇洒哥</d><d p="39.51200,1,25,16777215,1727942034,0,1bb3407b,1684858919241134848,9">三语广播懂了。</d><d p="293.66600,1,25,16777215,1727945688,0,4b785fdc,1684889573202775040,9">祥林嫂</d><d p="71.03900,1,25,16777215,1728049449,0,9e96d826,1685759980151635200,9">200蚊系重庆大厦咩</d><d p="239.15800,1,25,16777215,1728052915,0,35ba3a8f,1685789053985283840,8">边度友次子</d><d p="304.24600,5,25,16707842,1728058837,0,f609994a,1685838728461064448,10">回屯门了</d><d p="124.47400,1,25,16777215,1728070912,0,a7813eb2,1685940023997797376,11">做一晚泥工</d><d p="191.68800,1,25,16777215,1728083845,0,7be1486,1686048511500356864,9">黄碟（指正）</d><d p="254.06300,1,25,16777215,1728083960,0,7be1486,1686049476148382720,11">这就是卤煮（神似幻听）</d><d p="94.63400,1,25,16777215,1728087222,0,b66815a2,1686076845508663552,9">蚌埠住了</d><d p="290.66300,5,25,16777215,1728095903,0,22bb7d91,1686149664044547072,10">上水屋企</d><d p="183.57900,1,25,16777215,1728096686,0,496ff9c0,1686156233121790976,9">斯人已逝</d><d p="229.35800,1,25,15138834,1728099695,0,c897105b,1686181477227955200,9">珠人</d><d p="75.83300,1,25,16777215,1728101453,0,7abb3bba,1686196218772755200,11">甘便宜！</d><d p="33.05900,1,25,16777215,1728105658,0,c989a3eb,1686231498153325312,11">《电车》</d><d p="205.20000,1,25,16777215,1728107409,0,a4678217,1686246185146576640,11">缺黄碟的。去看广西版</d><d p="181.65700,1,25,16777215,1728107537,0,ebc0b911,1686247259602034944,9">永远怀念</d><d p="297.96400,1,25,16777215,1728109809,0,f69515c5,1686266314090231808,10">屯门</d><d p="265.97500,1,25,16777215,1728110892,0,f540f72d,1686275398239015680,9">吹水哈哈</d><d p="86.75800,1,25,16777215,1728111915,0,9271c2fa,1686283985145950720,9">加油！</d><d p="120.55400,1,25,16777215,1728113601,0,5b6aaf50,1686298123289176320,9">潇洒哥</d><d p="356.91500,5,25,14811775,1728113883,0,10c8148a,1686300493044818176,10">虽然政治不正确，但是这里插一手《薄情歌》就好了</d><d p="102.68200,1,25,16777215,1728115139,0,c6e0691b,1686311030369908480,9">钓蟹钓蟹</d><d p="111.87800,5,25,15138834,1728115167,0,c6e0691b,1686311265284361728,10">钓蟹钓蟹，我中意钓蟹，钓蟹多欢乐~</d><d p="247.07100,1,25,16777215,1728117250,0,a62bebb8,1686328737463022592,9">我滴friend（好</d><d p="306.37000,5,25,16777215,1728123182,0,1103141f,1686378494583923456,11">回大埔了</d><d p="217.92800,1,25,16777215,1728123828,0,3cc60595,1686383915293673984,9">昆山花桥表示很淦</d><d p="198.57900,1,25,16777215,1728125895,0,4fe638db,1686401258145936384,9">waitar~</d><d p="217.52600,1,25,16777215,1728131311,0,fe9db55d,1686446686920571392,8">大红花桥</d><d p="19.50000,5,25,16777215,1728142310,0,504dab23,1686538957975794176,10">柯 士 甸 站</d><d p="182.34500,1,25,16777215,1728146089,0,28e3d554,1686570656856604928,9">缅怀</d><d p="156.50800,1,25,16777215,1728188918,0,5d27ad5d,1686929927683641344,10">唔系条野太郎？</d><d p="100.03400,1,25,16777215,1728191323,0,3864aacd,1686950108728352768,9">一股强劲吊蟹音乐传黎</d><d p="194.00700,5,25,16646914,1728200199,0,1f27b6e0,1687024559066768128,10">nia nia nia nia nia nia!</d><d p="153.48200,1,25,16777215,1728205975,0,e46dd28f,1687073012421221632,8">要夹成世嘅</d><d p="289.52000,1,25,16777215,1728206181,0,e46dd28f,1687074744207381248,9">礼尚往来（</d><d p="60.53100,5,25,16777215,1728206683,0,b0141f6b,1687078952168040704,10">《俾面派对》</d><d p="280.75100,1,25,15138834,1728207246,0,b3e6c8b6,1687083673965264384,11">300呎巨宅</d><d p="92.57700,5,25,16777215,1728207437,0,a1cd550d,1687085282748515072,10">旺 角</d><d p="170.88500,1,25,16777215,1728207580,0,7e97206b,1687086474585033472,9">罗湖人叫一声</d><d p="240.47400,5,25,16777215,1728207610,0,a1cd550d,1687086725966568960,10">大 家 乐</d><d p="57.55600,1,25,16777215,1728210900,0,e45f6fbb,1687114330258927104,9">香港下雪，我怎么会做这样的梦</d><d p="115.15900,5,25,15138834,1728216365,0,8c928a87,1687160172885296640,10">点解係翻唱（确信）</d><d p="181.55900,5,25,16707842,1728216451,0,8c928a87,1687160897132533504,10">Mamba out!</d><d p="191.19800,1,25,16777215,1728221087,0,d325f79f,1687199782919930624,9">刘德华广告</d><d p="140.68300,1,25,16777215,1728221142,0,e60f0208,1687200244183667456,9">我缺的那冷冷冷谁来给我补啊</d><d p="99.80800,1,25,16777215,1728222137,0,b7509fc5,1687208587199280128,9">钓蟹钓蟹我钟意钓蟹</d><d p="352.10800,5,25,6737151,1728225839,0,2cb9a7c1,1687239649653168128,10">香港乐坛依然存在，但关注的人变少了.jpg</d><d p="354.79300,5,25,16777215,1728228156,0,34f61e5c,1687259081016363008,10">唔紧，東北也有會講白話 聽懂白話嘅人哋</d><d p="224.10400,1,25,16777215,1728229322,0,f2d30328,1687268859658665984,11">我月晶美莱</d><d p="105.64000,1,25,16777215,1728235192,0,84dce544,1687318108128082944,9">狠狠的钓蟹</d><d p="255.80000,5,25,16777215,1728235983,0,56fa7c7d,1687324741520480768,10">这下听懂了</d><d p="287.81000,1,25,16777215,1728239159,0,ce0de53d,1687351385869473024,9">菲佣真却大德了hhh</d><d p="254.37000,1,25,16777215,1728242934,0,1406583b,1687383050247563776,8">这个字不是和制汉字，原来就有的</d><d p="312.95200,1,25,16777215,1728255086,0,b400661c,1687484983503537408,8">什么动静？</d><d p="47.40600,1,25,16777215,1728265395,0,2efb94d2,1687571467056925184,9">组乐队，去红馆搞演出（doge）</d><d p="113.41600,1,25,16777215,1728272925,0,b29cc354,1687634628233953536,9">为什么不是做一晚泥工</d><d p="38.23200,5,25,15138834,1728281090,0,35f703a5,1687703125890242048,11">从九龙上车的（确信）</d><d p="353.17400,5,25,9487136,1728287496,0,f1888a0d,1687756861677353472,10">嗨呀这是为什么呢</d><d p="23.29900,5,25,15138834,1728290215,0,2bf084d2,1687779668768243712,10">佐敦</d><d p="92.07300,5,25,15138834,1728290354,0,2bf084d2,1687780836017902080,10">铜锣湾时代广场</d><d p="322.99800,5,25,15138834,1728290639,0,2bf084d2,1687783228054615552,10">aughhhhhhhhh</d><d p="283.18200,1,25,16777215,1728298044,0,49dab639,1687845343155128064,11">凸（^▽^）凸</d><d p="348.60000,1,25,16777215,1728301258,0,464ba9d3,1687872306531103488,11">家驹！</d><d p="357.33000,1,25,16777215,1728301279,0,464ba9d3,1687872485879773952,9">原谅我这一生不羁放纵爱自由</d><d p="289.65200,1,25,16777215,1728301768,0,c8fafaa1,1687876581550286848,9">菲佣笑的相似</d><d p="346.33100,1,25,16777215,1728301845,0,c8fafaa1,1687877230845580288,9">30几年前</d><d p="224.29900,5,25,16707842,1728306385,0,49ea2949,1687915316920990464,10">【吉川富隆】</d><d p="233.65500,5,25,16707842,1728306454,0,49ea2949,1687915896271686912,10">【柑蕉桔梨萝柚】</d><d p="219.94100,1,25,16777215,1728310320,0,b2a7d772,1687948326093325824,9">大红花轿i love u()</d><d p="311.95900,1,25,16777215,1728317116,0,ef76ad36,1688005335400490240,10">返上水了</d><d p="293.90000,5,25,16777215,1728319047,0,9858d998,1688021534222028032,10">薄 扶 林 村</d><d p="93.15800,1,25,16777215,1728349459,0,190e6ff,1688276648325935616,9">四驱小子</d><d p="14.01300,1,25,16777215,1728355393,0,6f9c7b90,1688326426475964672,9">不行, 太有禮貌了</d><d p="28.83500,5,25,15138834,1728362343,0,d9a288de,1688384722117884928,10">出音未来</d><d p="32.36400,1,25,16777215,1728395418,0,82067b63,1688662178103801600,9">味好沖</d><d p="182.23700,1,25,16777215,1728395572,0,e191a271,1688663466560493824,9">昔人已乘黄鹤去</d><d p="264.84800,1,25,16777215,1728400931,0,af76200c,1688708423987936512,10">岩啊 语言用来沟通 听得明就得</d><d p="31.42800,5,25,16776960,1728406452,0,e7310b83,1688754738121731840,10">调理农务</d><d p="102.62500,1,25,16777215,1728408511,0,c2be6dd7,1688772006365365504,9">做一晚泥工</d><d p="67.29500,1,25,16777215,1728411984,0,aa8cf84e,1688801141703602688,11">一闪而过</d><d p="145.83700,1,25,16777215,1728436016,0,5aca76ca,1689002737511118848,9">有冇乜我可以帮到你＝how can I help you？</d><d p="260.05100,1,25,16777215,1728451794,0,f18a98e5,1689135093396355072,9">広東語おねがいします</d><d p="140.12800,1,25,16777215,1728459529,0,43daa3d6,1689199980436804352,11">PGM啊哈哈哈哈哈</d><d p="177.89000,1,25,16777215,1728460731,0,f20325ce,1689210061488026880,9">罗湖口岸哈哈哈哈哈（不是蛇口！？</d><d p="102.75500,1,25,16777215,1728473409,0,cd6aedd9,1689316414072602368,9">钓蟹钓蟹</d><d p="276.94600,1,25,16777215,1728539063,0,dd3df801,1689867161378043136,11">這個英語夾得太對了</d><d p="276.94600,1,25,16777215,1728539074,0,dd3df801,1689867248477012736,10">這個英語夾得太對了</d><d p="106.48700,1,25,16777215,1728628097,0,63ebe71d,1690614034514269952,9">钓蟹钓蟹</d><d p="90.15500,1,25,16777215,1728656631,0,a6982f51,1690853390315774464,9">井芹仁菜龙卷风！</d><d p="226.36200,1,25,16777215,1728657280,0,9c2a95ac,1690858835285800192,11">我叫边度有次子</d><d p="193.96800,5,25,16707842,1728664769,0,4b7c69b9,1690921660598996224,10">桀桀桀桀桀桀桀桀桀桀桀桀桀桀桀</d><d p="97.86800,1,25,16777215,1728703697,0,b58e72c,1691248209026450176,9">该钓蟹了</d><d p="181.87000,1,25,16777215,1728703796,0,b58e72c,1691249042635972352,9">做一点微小的贡献</d><d p="96.71600,5,25,15138834,1728714692,0,5e5790fb,1691340446023950336,10">出音味来</d><d p="8.67100,1,25,16777215,1728735758,0,9c92ee78,1691517152470768896,10">听上去像广州的</d><d p="22.22800,1,25,16777215,1728735779,0,9c92ee78,1691517335535526144,8">对不是香港口音，是广东的</d><d p="76.50300,1,25,16777215,1728747036,0,8a78f7d9,1691611766649334272,9">宜家用app有200喎，不過未包稅</d><d p="184.62200,1,25,16777215,1728796859,0,5b203eb2,1692029707224419584,9">永远怀念</d><d p="42.27800,1,25,16777215,1728824796,0,cfafe87b,1692264058927631872,9">我嘞个Beyond啊（双厨狂喜</d><d p="265.22900,1,25,16777215,1728842420,0,709e8b95,1692411904452641536,8">么嘢系胶流？</d><d p="70.39800,1,25,16777215,1728907326,0,855de081,1692956370997117952,9">一 粥 面</d><d p="302.61300,1,25,16777215,1728914861,0,fdcc0a64,1693019585684726272,11">非佣也可以组乐队</d><d p="276.92600,1,25,16777215,1728924615,0,3984f7b9,1693101400533251328,9">很大（指20平方米）</d><d p="104.52500,1,25,16777215,1728932651,0,c2be6dd7,1693168816697398784,9">做一晚泥工</d><d p="127.30400,5,25,9033215,1728991209,0,ba3fcf2e,1693660034162039296,10">有没有可能，你的声音也很man</d><d p="133.49700,1,25,16777215,1729075367,0,e78cdf36,1694365999320751872,11">soulmate难绷</d><d p="15.16600,1,25,16777215,1729158431,0,b6b27b4f,1695062791226563584,9">《少女》</d><d p="104.31600,5,25,16707842,1729172577,0,d36dac3c,1695181457623993344,10">追寻一片冷的风！！！</d><d p="227.86800,1,25,14811775,1729177146,0,f18a98e5,1695219784536842496,9">安川良子</d><d p="108.90700,5,25,16765698,1729269281,0,791224e4,1695992673951477248,10">BGM:风云香港仔</d><d p="93.64000,1,25,16777215,1729308927,0,6a64475e,1696325245071288832,9">ifc（确信</d><d p="133.48700,1,25,16777215,1729451868,0,904f699a,1697524318940208128,9">尤里乌斯.凯撒</d><d p="346.53200,1,25,16777215,1729452194,0,904f699a,1697527058617411328,10">黄家驹！也适用于现在的国内乐坛</d><d p="146.65000,5,25,16777215,1729515533,0,36888ab2,1698058379299340544,10">出音味来</d><d p="319.31600,5,25,16777215,1729515881,0,36888ab2,1698061306277428480,10">TOYOTA</d><d p="279.08000,5,25,16776960,1729575230,0,694793f,1698559160968967424,10">HK能有多大</d><d p="45.97700,1,25,16777215,1729577906,0,4a70ed2b,1698581608254717952,9">BYD（即答</d><d p="24.18100,1,25,41194,1729699494,0,30fc4567,1699601560042017280,11">咖喱鱼蛋？</d><d p="91.48900,1,25,16777215,1729729334,0,95ea4926,1699851877372016896,9">四驱战士在行动</d><d p="279.91300,1,25,16777215,1729729607,0,95ea4926,1699854165490711808,8">如果自然的一句英语</d><d p="288.38000,1,25,16777215,1729741978,0,ca09818c,1699957938686557952,9">不是越南难民？</d><d p="159.41100,1,25,16777215,1729773257,0,913ac29a,1700220329051503872,8">我嘞个大祥老师啊</d><d p="220.91800,1,25,16777215,1729855592,0,732d8c8e,1700911003883955712,10">昆山花桥是吧</d><d p="184.92700,5,25,16707842,1729857947,0,c2a6b6ec,1700930760464849152,10">是您演的吗，那给我来一张吧</d><d p="30.92200,1,25,16777215,1730050575,0,2da95d97,1702546639115530496,9">ong拟嘛ong</d><d p="21.78800,1,25,16777215,1730130409,0,733fe3a0,1703216338677432320,9">柯士甸</d><d p="146.97300,1,25,16777215,1730271177,0,f32a345c,1704397185585667072,9">这句是侍应（服务员）常用的对答</d><d p="144.98000,1,25,16777215,1730345679,0,f81665c4,1705022152023557888,9">笑死我了</d><d p="105.99400,1,25,16777215,1730360698,0,fa825b44,1705148140853882624,11">做一碗泥工</d><d p="324.82700,1,25,16777215,1730899848,0,a4697a3e,1709670860283497728,10">猫：我谢谢你</d><d p="175.50300,1,25,16777215,1730912722,0,2738e034,1709778851984311552,11">做下一个mirror</d><d p="221.76400,1,25,16777215,1730912780,0,2738e034,1709779344865586432,11">小 北 花 圈</d><d p="341.01200,1,25,16777215,1730912931,0,2738e034,1709780609490184704,9">不是去无线演技培训班？</d><d p="135.58900,1,25,16777215,1731157476,0,624649c6,1711831996575524352,10">看过的第一个拿这方面当槽点的（哈哈哈哈）</d><d p="145.83500,5,25,15138834,1731252314,0,16d1fb2e,1712627557755150336,10">小孩姐：八意永琳   桃香：博丽灵梦</d><d p="278.75000,1,25,16777215,1732466529,0,7a0e3c56,1722813135611514368,9">超商呢</d><d p="275.68800,1,25,16777215,1732638982,0,1fac8ccd,1724259768777853952,9">在hk有很大的家（？）</d><d p="18.97300,1,25,16777215,1732711671,0,360a3b94,1724869528649346560,9">一落地铁就有鱼蛋档</d><d p="106.89500,1,25,16777215,1733159280,0,69286d2e,1728624349826689792,9">做一晚泥工</d><d p="183.28700,1,25,16777215,1733626983,0,7635b14e,1732547721702943232,9">斯人已逝</d><d p="99.75700,1,25,16777215,1733648363,0,66365077,1732727073975439104,9">做一晚泥工</d><d p="27.16300,1,25,16777215,1733769955,0,2e0dee44,1733747064275899136,9">物价正确，深圳1蚊1粒</d><d p="274.93800,1,25,16777215,1734004304,0,d0f1c51d,1735712920509620992,11">金鱼佬</d><d p="324.31300,1,25,16777215,1735114957,0,2e375099,1745029756212227328,9">is that a dog？</d><d p="319.01700,1,25,15138834,1736026225,0,1b2dd312,1752674023319540224,8">谁把摩托开进来了？</d><d p="231.33900,1,25,16777215,1736481430,0,6117c023,1756492566771598848,10">原来是明日香啊</d><d p="42.54200,5,25,41194,1736486233,0,d426092b,1756532852708796160,10">广铁U彩提醒你</d><d p="346.91700,1,25,16777215,1736513846,0,f9120721,1756764487526010368,8">黄家驹</d><d p="11.34400,1,25,16777215,1737369302,0,9cedb1aa,1763940569123512832,8">香 港 民 俗</d><d p="144.47000,1,25,16777215,1737816617,0,472ac1,1767692926776918528,9">七线呐</d><d p="101.19300,1,25,16777215,1737889053,0,7b7e1f61,1768300561436166400,9">做一晚泥工</d><d p="195.66200,5,25,16707842,1738061645,0,63090529,1769748364192328192,10">卖咸碟</d><d p="314.85900,1,25,16777215,1738333837,0,2a1fdb72,1772031677666382080,10">开头鼻鼾确实很大声</d><d p="22.11200,5,25,15772458,1738595883,0,a423a9c4,1774229879651315968,10">真的像柯士甸（）</d><d p="220.59500,5,25,16707842,1738640781,0,634fdd4e,1774606508806735360,10">faq</d><d p="253.97700,1,25,16777215,1738653485,0,2cfe24b3,1774713084116647168,8">黯 然 销 魂 饭</d><d p="300.92500,1,25,16777215,1738653543,0,2cfe24b3,1774713569573723904,10">深水埗</d><d p="326.70700,1,25,41194,1738895508,0,984627ed,1776743312741908224,10">哈基米：多兰谢你</d><d p="243.48200,1,25,16777215,1738987631,0,81a82061,1777516101468057088,9">标准日语发音</d><d p="73.94500,1,25,16777215,1739109311,0,de3ba4e5,1778536823808237824,11">诗人握持</d><d p="155.21600,5,25,8700107,1739109417,0,de3ba4e5,1778537717782247168,10">丰川祥子没绷住</d><d p="179.54400,5,25,16707842,1739153106,0,718b535e,1778904202794904064,10">man！</d><d p="359.47800,5,25,15138834,1739189764,0,4159d8d7,1779211715566110464,10">还真是！</d><d p="17.65500,1,25,16777215,1739208373,0,8c35cab8,1779367822226082560,9">霍！乌蝇哥係度卖鱼蛋啊</d><d p="181.90600,5,25,16777215,1739422389,0,6e2475e,1781163113388455168,10">永远怀念</d><d p="197.67400,1,25,16777215,1739491307,0,c6a6cb64,1781741244784180480,9">改成免费的了哈哈哈</d><d p="113.93700,1,25,16777215,1740452743,0,bc0168c4,1789806346561219328,9">这不对吧（狗头）</d><d p="75.76900,5,25,15138834,1740666444,0,889e9b24,1791599004413438976,10">山田凉附体</d><d p="66.56100,1,25,16777215,1740935665,0,2100549c,1793857398193228544,9">九龙冰室</d><d p="28.20000,1,25,16777215,1741004430,0,cd043490,1794434238222364416,9">旺角卡门</d><d p="194.65200,1,25,16777215,1741967916,0,6c5d2b6c,1802516544816198144,11">waiter n.服务员</d><d p="323.94100,5,25,15138834,1742173111,0,b5af2ced,1804237841115572992,10">IS THAT A DOG？</d><d p="34.45100,1,25,16777215,1742396052,0,1a052820,1806108007021645824,9">下一站:深水埗</d><d p="10.25100,5,25,16707842,1742528281,0,5f49bd53,1807217224017702400,10">《香  港  西  九  龙  站》</d><d p="57.46500,5,25,16707842,1742564713,0,2916243c,1807522842188267520,10">好一个特异人士</d><d p="227.14900,5,25,16777215,1742564983,0,2916243c,1807525106726600960,10">明日香……</d><d p="241.68900,5,25,16707842,1742565038,0,2916243c,1807525567152148224,10">呢個唔係大家樂嘅？</d><d p="14.78000,5,25,15138834,1742607794,0,a6c9dedd,1807884226876472576,10">《八达通》</d><d p="0.00000,1,25,16777215,1742728187,0,e7286573,1808894159076595712,10">终于找到咱港力！</d><d p="294.81700,1,25,16777215,1743597846,0,58c1e379,1816189388628319488,10">可是rupa是尼泊尔人啊</d><d p="37.21700,1,25,16777215,1743871297,0,d0eef661,1818483259760334848,9">丢雷楼咩</d><d p="349.98600,1,25,10546688,1744010348,0,56b6d39c,1819649703990720000,8">md突然严肃起来了qwq</d><d p="118.73400,5,25,16777215,1744523416,0,957f09fd,1823953628231175168,10">仲未脱富，就要督隆！</d><d p="365.52800,1,25,16777215,1727541342,0,b6e504ca,1681497666838124544,9">泪目</d><d p="403.03900,1,25,16777215,1727541873,0,68bbfd64,1681502126767124736,11">我去，说的真好</d><d p="435.26100,1,25,16777215,1727541919,0,68bbfd64,1681502508641594624,10">牛</d><d p="465.96000,1,25,16777215,1727541955,0,68bbfd64,1681502811126356224,9">不是空箱子，本来想跳过的，但没想到这首也很好听啊</d><d p="494.75200,1,25,16777215,1727541984,0,68bbfd64,1681503052240014848,10">人类群星闪耀时。。。。</d><d p="519.16000,1,25,16777215,1727542008,0,68bbfd64,1681503257056436736,11">ao听</d><d p="525.07600,1,25,16777215,1727542312,0,68bbfd64,1681505806555753472,10">看来是还有下集的样子捏</d><d p="392.70700,1,25,16777215,1727545338,0,8051a4ee,1681531192329086208,11">升华了</d><d p="459.51700,1,25,16777215,1727546872,0,108cec7c,1681544057324769792,10">又看一集</d><d p="368.38400,1,25,16777215,1727549032,0,48dfd0c2,1681562176886551808,11">确实…虽然听，但是多数都是听粤语老歌多…</d><d p="421.17900,1,25,16777215,1727549097,0,48dfd0c2,1681562726181043712,11">这里真的太摇滚了，有心了up主</d><d p="499.77200,1,25,16777215,1727549203,0,48dfd0c2,1681563608368965376,11">情绪对上了啊</d><d p="383.40200,5,25,16777215,1727568694,0,db824e08,1681727113486650624,10">致敬传奇预设播放量103</d><d p="381.65700,1,25,16777215,1727571897,0,e11c8218,1681753981367536384,9">泪目</d><d p="421.41900,5,25,16707842,1727575838,0,11252aad,1681787040385884672,10">顶你，太摇滚啦！撑粤语！</d><d p="422.47300,1,25,16777215,1727580338,0,27937529,1681824792015915264,9">升华！</d><d p="449.64100,1,25,16777215,1727580372,0,98cea329,1681825075097961728,9">小孩的声线好成熟，爱了</d><d p="367.13100,1,25,16777215,1727590089,0,3d2d0a16,1681906587721351168,9">个人感觉现在的粤语歌没以前的那么耐听，，歌单里的歌增增减减时候还是只剩Beyond</d><d p="454.34100,1,25,16777215,1727592319,0,e2f6d598,1681925294963086592,11">打呼噜声线（</d><d p="363.03300,1,25,16777215,1727596891,0,9aaa5c11,1681963645263186944,9">大多新出嘅粤语歌又真系唔掂啊</d><d p="381.72800,1,25,16777215,1727596923,0,d91568e4,1681963918161094400,8">泪目</d><d p="386.82300,1,25,16777215,1727599494,0,1bf78f25,1681985479526100736,10">103</d><d p="367.54900,1,25,16777215,1727608179,0,ba02a6dd,1682058336374043648,9">升华了</d><d p="450.59600,1,25,16777215,1727609287,0,9ec86303,1682067631387226880,11">目标红馆</d><d p="442.60700,1,25,16777215,1727609754,0,fa209473,1682071552357105152,11">好浑厚的嗓音啊</d><d p="421.21500,5,25,16777215,1727614744,0,6ecbf28e,1682113408919288320,10">没绷住</d><d p="480.29800,1,25,16777215,1727618112,0,dde55565,1682141658713564928,10">又睇一集</d><d p="467.92600,1,25,16777215,1727619110,0,1075c959,1682150036290967808,10">最结合本地的一集</d><d p="363.92000,1,25,16777215,1727622165,0,ffe44840,1682175657482180352,11">我宁愿反复听校长94大球场演唱会也不想听现在的歌</d><d p="443.85900,1,25,16777215,1727622708,0,d7d9a5e1,1682180217823057152,10">又看一集</d><d p="458.27900,1,25,16777215,1727625304,0,53d247b1,1682201992862383360,9">变声期到了</d><d p="393.05900,5,25,15138834,1727627086,0,4b080243,1682216938366888192,11">你的歌声就是你内心的呐喊啊！</d><d p="361.54600,1,25,16777215,1727627093,0,ad4d5d6e,1682216996894292736,11">还真是，，，听jrock了</d><d p="451.04500,1,25,16777215,1727629331,0,27937529,1682235776874118656,10">我觉得呢度放幸福之歌都好适合</d><d p="423.57100,1,25,16777215,1727630875,0,6446afa3,1682248724799618048,9">太摇滚啦！！</d><d p="381.14000,1,25,16777215,1727650573,0,cded5df9,1682413967835834624,10">粤语歌规则太严，门槛太高</d><d p="476.90500,1,25,16777215,1727664821,0,64220112,1682533482263320320,10">这么好听woc</d><d p="446.62100,5,25,15138834,1727668114,0,d348349,1682561109875788032,10">主唱太拼命了（</d><d p="375.52600,1,25,16777215,1727679320,0,fb06322f,1682655113271348480,9">升华了</d><d p="455.57600,1,25,16777215,1727679883,0,8470c934,1682659838322282752,8">又睇一集</d><d p="457.60100,5,25,16777215,1727683083,0,330394e3,1682686677195436032,10">又睇咗一集</d><d p="450.52900,5,25,16646914,1727693603,0,9ac02259,1682774929252252416,10">又睇一集</d><d p="426.33900,1,25,16777215,1727695990,0,7e47ea31,1682794950436009984,11">改得真好</d><d p="438.49900,1,25,16777215,1727696017,0,7e47ea31,1682795177062638336,9">我c，改得这么厉害啊</d><d p="383.30900,1,25,16777215,1727704958,0,56a35858,1682870178398763264,11">得108沃</d><d p="447.17000,1,25,16777215,1727706623,0,5105bf15,1682884148458500096,9">变声期。</d><d p="407.01900,1,25,16777215,1727709359,0,7382386b,1682907097669218304,9">好的作品是有作者的自我表达的</d><d p="510.27900,1,25,16777215,1727710084,0,bccd6f42,1682913180038775552,11">我要现在就看到第二集！</d><d p="460.81900,1,25,16777215,1727721792,0,61185650,1683011393374303232,11">吴卓羲倾情配音献唱</d><d p="504.30900,1,25,16777215,1727733712,0,bfa04249,1683111382553809408,10">再恨 仍照燿</d><d p="448.36200,5,25,16777215,1727751263,0,4868016e,1683258616565765632,11">第一次用男女老少形容一个人</d><d p="417.20200,1,25,16777215,1727751452,0,a210d120,1683260198473405696,10">升华了，必须三连</d><d p="376.44900,5,25,16776960,1727753543,0,a616f212,1683277736677954048,10">呜呜呜呜家驹</d><d p="417.32700,5,25,16777215,1727758438,0,d6135ef2,1683318804525899264,11">太摇滚了</d><d p="373.49500,1,25,16777215,1727778803,0,5c20e8cb,1683489633696244480,8">dear myself确实很好听</d><d p="369.65600,1,25,16777215,1727791645,0,2b3e19fe,1683597364504256768,10">报！听的最多是汉语！</d><d p="444.00300,1,25,16777215,1727794571,0,d07b090d,1683621907734120448,9">吼吼这都有sunny听哦</d><d p="366.76000,1,25,16777215,1727799317,0,17b91c5f,1683661724336783872,9">最有本地文化思考的一集</d><d p="366.76000,1,25,16777215,1727799322,0,17b91c5f,1683661763251384576,9">最有本地文化思考的一集</d><d p="361.26800,1,25,16777215,1727800372,0,96ca478e,1683670570929239040,10">中區人行天橋</d><d p="398.90400,1,25,16777215,1727806929,0,d070e2a,1683725571601226240,10">泪目</d><d p="393.51000,5,25,16707842,1727825295,0,bf07b8c2,1683879643016530432,10">泪目</d><d p="485.70500,1,25,16777215,1727839577,0,27937529,1683999448310687488,11">目标！红馆！</d><d p="451.65100,1,25,16777215,1727879371,0,e903e512,1684333257615602688,8">Mirror的Jer版本也好听哦</d><d p="389.93200,1,25,16777215,1727883780,0,5a097377,1684370245395027200,10">有老歌的水平我就听，没有真听不下去</d><d p="474.70700,5,25,16707842,1727884963,0,a616f212,1684380174117841152,11">红衣服，主唱，嗓音浑厚，长头发，你是？</d><d p="421.11400,1,25,16777215,1727889934,0,278f1736,1684421873327112704,10">谢谢在2024还在坚持粤语歌的人们！</d><d p="462.57100,5,25,16777215,1727898988,0,885440f9,1684497822684623360,10">又睇一集</d><d p="406.50900,1,25,16777215,1727929738,0,9877d228,1684755774158724352,11">泪目</d><d p="360.75600,5,25,16777215,1727933871,0,d7aa5eb6,1684790439796020992,10">中环码头</d><d p="433.38400,1,25,16777215,1728084222,0,7be1486,1686051672361030656,10">太摇滚baby了</d><d p="394.40400,1,25,16777215,1728087809,0,b66815a2,1686081770527624448,9">格调最高的一集</d><d p="384.52900,5,25,16777215,1728090919,0,135fbf13,1686107857529000192,10">从广西少女乐队来的，o瘪太入脑了</d><d p="410.57000,1,25,16777215,1728101608,0,bc245e1,1686197517370305792,10">格局大了</d><d p="519.15000,1,25,16777215,1728123977,0,bae9258d,1686385164290228736,10">嘴型居然对上了</d><d p="372.35800,1,25,16777215,1728133922,0,5e9827c7,1686468588325803264,11">升华了，泪目</d><d p="388.53900,1,25,16777215,1728135915,0,c32bdcfa,1686485309632465664,11">我台湾人也很少听闽南语新歌了</d><d p="489.80700,1,25,16777215,1728190879,0,b721818f,1686946377433476352,10">又睇一集</d><d p="440.62400,5,25,16646914,1728193732,0,f0b09358,1686970316649400576,10">虽然我听不懂粤语，但是觉得这首歌真不错</d><d p="432.06700,1,25,16777215,1728225924,0,d6aa2538,1687240357894984960,11">又看了一集</d><d p="435.47100,1,25,16777215,1728239357,0,ce0de53d,1687353045068900864,9">这台词改的真神了</d><d p="510.29200,1,25,16777215,1728263052,0,157ac2f6,1687551814670546176,10">又看一集</d><d p="374.88200,1,25,16777215,1728308223,0,616f090a,1687930732951767040,10">啊啊啊真的很痛心啊</d><d p="424.15600,1,25,16777215,1728391990,0,98fadf6b,1688633423566218240,9">这真摇滚</d><d p="403.55800,5,25,15138834,1728484775,0,43ffafd8,1689411759510766080,10">撑广东歌！撑粤语！</d><d p="435.47500,1,25,16777215,1728556244,0,8b3e49c,1690011287402648320,8">你的吉他怎么是四根线</d><d p="436.28400,5,25,16707842,1728665042,0,4b7c69b9,1690923948432454144,10">又看一集</d><d p="464.31800,1,25,16777215,1728953922,0,672effc8,1693347246676041216,11">街头军训</d><d p="467.45500,1,25,16777215,1729096776,0,53406651,1694545591524292864,11">迷星叫</d><d p="402.76300,1,25,16777215,1729532234,0,a8f622e9,1698198483263576576,10">格局大了</d><d p="360.93200,1,25,16777215,1729569140,0,e9bc156c,1698508072777081088,8">我也是，粤语歌听的都是老歌了基本</d><d p="420.65600,5,25,16776960,1729768119,0,c6b921a0,1700177231336778752,10">花Q！</d><d p="393.30800,5,25,15138834,1729770928,0,334d411b,1700200789526380032,10">永远高唱我歌！走遍千里！！！</d><d p="426.17000,5,25,15138834,1730550540,0,b87c1c5c,1706740648533118976,10">逃跑的吉他手</d><d p="369.68500,5,25,15138834,1730811237,0,65d2d80f,1708927532994757120,10">保护粤语刻不容缓！</d><d p="478.79400,5,25,15138834,1731252743,0,16d1fb2e,1712631154446306048,10">是但丁！！！</d><d p="429.49600,5,25,16777215,1734357249,0,44569c97,1738673640318916096,10">致敬傳奇歸去來兮女士鍾洛海</d><d p="443.98800,5,25,41194,1736486765,0,d426092b,1756537312470225152,9">好man的嗓音啊（</d><d p="421.95700,1,25,41194,1738895669,0,984627ed,1776744665329439488,9">花桥ALL</d><d p="466.08300,1,25,16777215,1740936248,0,2100549c,1793862283894803712,8">卡点？</d></i>